README.md
setup.cfg
setup.py
estime2/__init__.py
estime2/age.py
estime2/aggregatepoptables.py
estime2/helper.py
estime2/metric.py
estime2/poptable.py
estime2/poptable_resultswrapper.py
estime2/subpoptables.py
estime2/vis.py
estime2.egg-info/PKG-INFO
estime2.egg-info/SOURCES.txt
estime2.egg-info/dependency_links.txt
estime2.egg-info/requires.txt
estime2.egg-info/top_level.txt
estime2/config/__init__.py
estime2/config/config.py
tests/__init__.py
tests/conftest.py
tests/integration/__init__.py
tests/integration/test_age.py
tests/integration/test_calculate_ages_to_modify_and_counter.py
tests/integration/test_provpoptable.py
tests/unit/__init__.py
tests/unit/test_calculate_ages_to_counter_in_pop.py
tests/unit/test_get_option.py
tests/unit/test_maychange.py
tests/unit/test_option_context.py
tests/unit/test_reset_option.py
tests/unit/test_set_option.py