Metadata-Version: 2.1
Name: estime2
Version: 0.1.2
Summary: Population table manipulation.
Home-page: https://gitlab.com/joon3216/estime2
Author: Christian Olivier Nambeu <christianolivier.nambeu@canada.ca>, Junkyu Park <junkyu.park@canada.ca>
License: MIT License
Platform: UNKNOWN
Classifier: Development Status :: 4 - Beta
Classifier: License :: OSI Approved :: MIT License
Classifier: Operating System :: OS Independent
Classifier: Programming Language :: Python
Classifier: Programming Language :: Python :: 3
Classifier: Programming Language :: Python :: 3.6
Classifier: Programming Language :: Python :: 3.7
Classifier: Programming Language :: Python :: 3.8
Requires-Python: >=3.6.1
